{"multipleChoiceTemplateData":{"type":"object","properties":{"backgroundImage":"https://d2o906d8ln7ui1.cloudfront.net/images/response_builder/background-green.png","titleText":"Test A.D.L.","primaryText":"Here is a fun plant question of the day. Which plant family does Asparagus belong to? Please choose one from the following.","choices":["No puedo","Necesito ayuda","Me cuesta","Puedo solo"],"choiceListType":"number","headerAttributionImage":"https://d2o906d8ln7ui1.cloudfront.net/images/response_builder/logo-world-of-plants-2.png","footerHintText":"Prueba a contestar, \"Un 3.\""}}}